jspcap/README.md
jspcap/__init__.py
jspcap/__main__.py
jspcap/all.py
jspcap/corekit/README.md
jspcap/corekit/__init__.py
jspcap/corekit/infoclass.py
jspcap/corekit/protochain.py
jspcap/corekit/version.py
jspcap/dumpkit/README.md
jspcap/dumpkit/__init__.py
jspcap/foundation/README.md
jspcap/foundation/__init__.py
jspcap/foundation/analysis.py
jspcap/foundation/extraction.py
jspcap/foundation/traceflow.py
jspcap/interface/README.md
jspcap/interface/__init__.py
jspcap/ipsuite/README.md
jspcap/ipsuite/__init__.py
jspcap/ipsuite/protocol.py
jspcap/ipsuite/application/README.md
jspcap/ipsuite/application/__init__.py
jspcap/ipsuite/internet/README.md
jspcap/ipsuite/internet/__init__.py
jspcap/ipsuite/link/README.md
jspcap/ipsuite/link/__init__.py
jspcap/ipsuite/pcap/README.md
jspcap/ipsuite/pcap/__init__.py
jspcap/ipsuite/pcap/frame.py
jspcap/ipsuite/pcap/header.py
jspcap/ipsuite/transport/README.md
jspcap/ipsuite/transport/__init__.py
jspcap/protocols/README.md
jspcap/protocols/__init__.py
jspcap/protocols/protocol.py
jspcap/protocols/raw.py
jspcap/protocols/application/README.md
jspcap/protocols/application/__init__.py
jspcap/protocols/application/application.py
jspcap/protocols/application/http.py
jspcap/protocols/application/httpv1.py
jspcap/protocols/application/httpv2.py
jspcap/protocols/internet/README.md
jspcap/protocols/internet/__init__.py
jspcap/protocols/internet/ah.py
jspcap/protocols/internet/hip.py
jspcap/protocols/internet/hopopt.py
jspcap/protocols/internet/internet.py
jspcap/protocols/internet/ip.py
jspcap/protocols/internet/ipsec.py
jspcap/protocols/internet/ipv4.py
jspcap/protocols/internet/ipv6.py
jspcap/protocols/internet/ipv6_frag.py
jspcap/protocols/internet/ipv6_opts.py
jspcap/protocols/internet/ipv6_route.py
jspcap/protocols/internet/ipx.py
jspcap/protocols/internet/mh.py
jspcap/protocols/link/README.md
jspcap/protocols/link/__init__.py
jspcap/protocols/link/arp.py
jspcap-1.0.0.dist-info/LICENSE.txt
jspcap-1.0.0.dist-info/METADATA
jspcap-1.0.0.dist-info/RECORD
jspcap-1.0.0.dist-info/WHEEL
jspcap-1.0.0.dist-info/entry_points.txt
jspcap-1.0.0.dist-info/top_level.txt
