Metadata-Version: 2.1
Name: jspcap
Version: 1.0.0
Summary: The `jspcap` module is deprecated and renamed as `pypcapkit`.
Home-page: https://github.com/JarryShaw/jspcap
Author: Jarry Shaw
Author-email: jarryshaw@icloud.com
License: GNU General Public License v3 (GPLv3)
Keywords: computer-networking pcap-analyzer pcap-parser
Platform: UNKNOWN
Classifier: Development Status :: 5 - Production/Stable
Classifier: Environment :: Console
Classifier: Environment :: MacOS X
Classifier: Environment :: Win32 (MS Windows)
Classifier: Intended Audience :: Developers
Classifier: License :: OSI Approved :: GNU General Public License v3 (GPLv3)
Classifier: Natural Language :: English
Classifier: Operating System :: MacOS
Classifier: Operating System :: Microsoft :: Windows
Classifier: Operating System :: Unix
Classifier: Programming Language :: Python
Classifier: Programming Language :: Python :: 3
Classifier: Programming Language :: Python :: 3.6
Classifier: Programming Language :: Python :: 3 :: Only
Classifier: Programming Language :: Python :: Implementation
Classifier: Programming Language :: Python :: Implementation :: CPython
Classifier: Programming Language :: Python :: Implementation :: PyPy
Classifier: Topic :: System :: Networking
Classifier: Topic :: Utilities
Requires-Python: >=3.6
Provides-Extra: Scapy
Provides-Extra: DPKT
Provides-Extra: PyShark
Requires-Dist: jsformat
Requires-Dist: chardet
Requires-Dist: setuptools
Provides-Extra: DPKT
Requires-Dist: dpkt; extra == 'DPKT'
Provides-Extra: PyShark
Requires-Dist: pyshark; extra == 'PyShark'
Provides-Extra: Scapy
Requires-Dist: scapy; extra == 'Scapy'
